sincei/ExponentialFamily.py
sincei/FragmentFFT.py
sincei/GLMPCA.py
sincei/GetStats.py
sincei/ParserCommon.py
sincei/ReadCounter.py
sincei/RegionQuery.py
sincei/TopicModels.py
sincei/Utilities.py
sincei/WriteBedGraph.py
sincei/__init__.py
sincei/_deprecated.py
sincei/_version.py
sincei/multimodalClustering.py
sincei/scBAMops.py
sincei/scBulkCoverage.py
sincei/scClusterCells.py
sincei/scCombineCounts.py
sincei/scCountQC.py
sincei/scCountReads.py
sincei/scFilterBarcodes.py
sincei/scFilterStats.py
sincei/scJSD.py
sincei/scPlotRegion
sincei/sincei.py
sincei/tests/__init__.py
sincei/tests/test_ExponentialFamily.py
sincei/tests/test_GLMPCA.py
sincei/tests/test_scCountReads.py
sincei/tests/test_tools.py
sincei/tests/_data/Ogfrl.gtf
sincei/tests/_data/SL2-1.bam
sincei/tests/_data/SL2-1.bam.bai
sincei/tests/_data/SL2-2.bam
sincei/tests/_data/SL2-2.bam.bai
sincei/tests/_data/test_barcodes.txt
sincei/tests/_data/test_regions.bed
sincei-0.5.2.dist-info/METADATA
sincei-0.5.2.dist-info/WHEEL
sincei-0.5.2.dist-info/entry_points.txt
sincei-0.5.2.dist-info/licenses/LICENCE.txt
sincei-0.5.2.dist-info/RECORD
