Metadata-Version: 2.4
Name: sincei
Version: 0.5.2
Summary: A user-friendly toolkit for QC, counting, clustering and plotting of single-cell (epi)genomics data 
Project-URL: Documentation, https://sincei.readthedocs.io/
Project-URL: Source, https://github.com/vivekbhr/sincei
Project-URL: Home-page, https://github.com/vivekbhr/sincei
Author: Vivek Bhardwaj, Fernando Sancho Gómez
Maintainer-email: Vivek Bhardwaj <v.bhardwaj@uu.nl>, Fernando Sancho Gómez <f.sanchogomez@uu.nl>
License: MIT license:
License-File: LICENCE.txt
Classifier: Intended Audience :: Science/Research
Classifier: Programming Language :: Python :: 3
Classifier: Topic :: Scientific/Engineering :: Bio-Informatics
Requires-Python: >=3.8
Requires-Dist: anndata
Requires-Dist: deeptools
Requires-Dist: gensim
Requires-Dist: leidenalg
Requires-Dist: mctorch-lib
Requires-Dist: mudata
Requires-Dist: networkx
Requires-Dist: pandas
Requires-Dist: python-igraph
Requires-Dist: scanpy
Requires-Dist: session-info
Requires-Dist: torch
Requires-Dist: umap-learn
Provides-Extra: dev
Requires-Dist: bump2version; extra == 'dev'
Requires-Dist: pre-commit; extra == 'dev'
Requires-Dist: twine>=4.0.2; extra == 'dev'
Provides-Extra: doc
Requires-Dist: ipython; extra == 'doc'
Requires-Dist: myst-nb; extra == 'doc'
Requires-Dist: readthedocs-sphinx-ext; extra == 'doc'
Requires-Dist: sphinx-argparse; extra == 'doc'
Requires-Dist: sphinx-autodoc-typehints; extra == 'doc'
Requires-Dist: sphinx-book-theme>=0.3.3; extra == 'doc'
Requires-Dist: sphinx-toolbox; extra == 'doc'
Requires-Dist: sphinx>=8; extra == 'doc'
Requires-Dist: sphinxcontrib-bibtex>=1.0.0; extra == 'doc'
Provides-Extra: test
Requires-Dist: pytest; extra == 'test'
